Metadata-Version: 2.1
Name: BankingSystems
Version: 0.0.2
Summary: Basic ATM system with several features: deposit, withdrawal, transfer, balance checks
Home-page: 
Author: Ahriel, Fatim, Conner, Soto
Author-email: ayoung08@rams.shepherd.edu
License: MIT
Keywords: banking system,ATM program
Classifier: Development Status :: 5 - Production/Stable
Classifier: Intended Audience :: Education
Classifier: Operating System :: Microsoft :: Windows :: Windows 10
Classifier: License :: OSI Approved :: MIT License
Classifier: Programming Language :: Python :: 3
License-File: LICENSE.txt
Requires-Dist: tkinter
